cilin/__init__.py
cilin/cilin.py
data/cilin_tree.json
cilin-0.0.3.dist-info/METADATA
cilin-0.0.3.dist-info/WHEEL
cilin-0.0.3.dist-info/top_level.txt
cilin-0.0.3.dist-info/RECORD
